LICENSE
MANIFEST.in
README.md
conftest.py
pytest.ini
setup.py
tox.ini
iostat/__init__.py
iostat/consts.py
iostat/csv.py
iostat/filters.py
iostat/main.py
iostat/parser.py
iostat/plotter.py
iostat/process.py
iostat/renderer.py
iostat/scatter.py
iostat/utils.py
iostat_tool.egg-info/PKG-INFO
iostat_tool.egg-info/SOURCES.txt
iostat_tool.egg-info/dependency_links.txt
iostat_tool.egg-info/entry_points.txt
iostat_tool.egg-info/requires.txt
iostat_tool.egg-info/top_level.txt
tests/fixtures/sample-iostat.png
tests/fixtures/sample_iostat.output
tests/fixtures/sample_iostat_11.7.3.output
tests/fixtures/sample_iostat_11.png
tests/fixtures/sample_iostat_killo.output
tests/fixtures/sample_iostat_sector.output
tests/fixtures/sample_iostat_small.output
tests/fixtures/sample_iostat_without_cpu.output