Metadata-Version: 2.1
Name: iostat-tool
Version: 0.3.1
Summary: parse and visualize iostat output
Home-page: https://github.com/t2y/iostat-tool
Author: Tetsuya Morimoto
Author-email: tetsuya.morimoto@gmail.com
License: Apache License 2.0
Keywords: iostat
Platform: unix
Platform: linux
Platform: osx
Platform: windows
Classifier: License :: OSI Approved :: Apache Software License
Classifier: Development Status :: 4 - Beta
Classifier: Intended Audience :: Developers
Classifier: Operating System :: Microsoft :: Windows
Classifier: Operating System :: MacOS :: MacOS X
Classifier: Operating System :: POSIX
Classifier: Programming Language :: Python :: 3
Classifier: Programming Language :: Python :: 3.8
Classifier: Programming Language :: Python :: 3.9
Classifier: Programming Language :: Python :: 3.10
Classifier: Programming Language :: Python :: 3.11
Classifier: Programming Language :: Python :: 3.12
Classifier: Programming Language :: Python :: 3 :: Only
Classifier: Programming Language :: Python :: Implementation :: CPython
Classifier: Programming Language :: Python :: Implementation :: PyPy
Classifier: Topic :: Software Development :: Libraries
License-File: LICENSE
